pulsee/__init__.py
pulsee/hamiltonians.py
pulsee/many_body.py
pulsee/nuclear_spin.py
pulsee/operators.py
pulsee/plot.py
pulsee/quantum_computing.py
pulsee/simulation.py
pulsee/spin_squeezing.py
pulsee-0.1.4.dist-info/LICENSE
pulsee-0.1.4.dist-info/METADATA
pulsee-0.1.4.dist-info/WHEEL
pulsee-0.1.4.dist-info/RECORD
