Metadata-Version: 2.1
Name: pulsee
Version: 0.1.4
Summary: Program for the Simulation of Nuclear Spin Ensemble Evolution
License: GPL-3.0-or-later
Author: Jiwoo Seo
Author-email: lemon6927@gmail.com
Requires-Python: >=3.11,<4.0
Classifier: License :: OSI Approved :: GNU General Public License v3 or later (GPLv3+)
Classifier: Programming Language :: Python :: 3
Classifier: Programming Language :: Python :: 3.11
Classifier: Programming Language :: Python :: 3.12
Requires-Dist: cython (<3)
Requires-Dist: ipykernel (>=6.29.0,<7.0.0)
Requires-Dist: ipyparallel (>=8.6.1,<9.0.0)
Requires-Dist: matplotlib (>=3.8.2,<4.0.0)
Requires-Dist: numpy (>=1.26.3,<2.0.0)
Requires-Dist: pandas (>=2.2.0,<3.0.0)
Requires-Dist: qutip (>=4.7.5,<5.0.0)
Requires-Dist: scipy (>=1.12.0,<2.0.0)
Requires-Dist: tqdm (>=4.66.1,<5.0.0)
